mdformat_recover_urls/__init__.py
mdformat_recover_urls/plugin.py
mdformat_recover_urls-0.0.2.dist-info/licenses/LICENSE
mdformat_recover_urls-0.0.2.dist-info/METADATA
mdformat_recover_urls-0.0.2.dist-info/WHEEL
mdformat_recover_urls-0.0.2.dist-info/entry_points.txt
mdformat_recover_urls-0.0.2.dist-info/top_level.txt
mdformat_recover_urls-0.0.2.dist-info/RECORD
