Metadata-Version: 2.4
Name: mdformat-recover-urls
Version: 0.0.2
Summary: mdformat plugin: recover relative and anchor URLs without percent-encoding
Author-email: nanarino <kogawananari@gmail.com>
License-Expression: MIT
Project-URL: github, https://github.com/holy-two/mdformat-recover-urls
Requires-Python: >=3.8
License-File: LICENSE
Requires-Dist: mdformat>=0.7.17
Requires-Dist: markdown-it-py>=2.2.0
Dynamic: license-file
